Metadata-Version: 2.1
Name: MakeSensAPI-Python
Version: 0.5.1
Summary: MakeSense API
Home-page: https://github.com/MakeSens-Data/MakeSensAPI_Python
Author: MakeSens G.Ch. DAPL
Author-email: miguelta281@gmail.com
License: GNU General Public License v3.0
Platform: UNKNOWN
Classifier: Programming Language :: Python :: 3
Classifier: Programming Language :: Python :: 3.9
License-File: LICENSE
